freq_divider/divide_by_10/divide10.v
module divide10(input clk,reset,
output reg clkout);
reg [2:0]count;
always@(posedge clk)begin
if(reset) begin
	clkout<=0;
	count<=0;
end
else if(count==4)begin
	count<=0;
	clkout<=~clkout;
end
else
	count<=count+1'b1;
end
endmodule

freq_divider/divide_by_10/divide10_tb.v

module tb;
reg clk,reset;
wire clkout;
divide10 uut(.clk(clk),.reset(reset),.clkout(clkout));
initial begin
clk=0;
forever #10 clk=~clk;
end
initial begin
$monitor("time=%0t clk=%b reset=%b clkout=%b",$time,clk,reset,clkout);
$dumpfile("divide_by_10.vcd");
$dumpvars;
reset=1;
#20 reset=0;
#100 $finish;
end
endmodule

freq_divider/divide_by_10/divide_by_10.vcd
$date
	Tue Aug 11 05:09:58 2026
$end
$version
	Icarus Verilog
$end
$timescale
	1s
$end
$scope module tb $end
$var wire 1 ! clkout $end
$var reg 1 " clk $end
$var reg 1 # reset $end
$scope module uut $end
$var wire 1 " clk $end
$var wire 1 # reset $end
$var reg 1 ! clkout $end
$var reg 3 $ count [2:0] $end
$upscope $end
$upscope $end
$enddefinitions $end
$comment Show the parameter values. $end
$dumpall
$end
#0
$dumpvars
bx $
1#
0"
x!
$end
#10
b0 $
0!
1"
#20
0"
0#
#30
b1 $
1"
#40
0"
#50
b10 $
1"
#60
0"
#70
b11 $
1"
#80
0"
#90
b100 $
1"
#100
0"
#110
1!
b0 $
1"
