fifo/asynchronous_fifo/design_code.v
//memory block
module memory(input wclk,rclk,
input w_en,r_en,
input [2:0]w_add,r_add,
input [7:0]wdata,
output reg [7:0]rdata);

reg [7:0]mem[0:7];

always@(posedge wclk)begin
if(w_en)
	mem[w_add]<=wdata;
end

always@(posedge rclk)begin
if(r_en)
	rdata<=mem[r_add];
end

endmodule


//write pointer handler

module write_handler(input wclk,w_rst,
	input w_en,
	input [3:0]r_gray_sync,
	output reg [3:0]w_bi_ptr,
	output reg [3:0]w_gray_ptr,
	output reg wfull);

reg [3:0]r_bi_sync;
wire [3:0]w_bi_ptr_temp;
always@(*)begin
r_bi_sync[3]=r_gray_sync[3];
r_bi_sync[2]=r_bi_sync[3]^r_gray_sync[2];
r_bi_sync[1]=r_bi_sync[2]^r_gray_sync[1];
r_bi_sync[2]=r_bi_sync[1]^r_gray_sync[0];
end
assign w_bi_ptr_temp=w_bi_ptr+1;

always@(posedge wclk or negedge w_rst)begin
	if(!w_rst)begin
		w_bi_ptr<=4'd0;
		w_gray_ptr<=4'd0;
		wfull<=1'b0;
	end
	else begin
		if(w_en && !wfull) begin
			w_bi_ptr<=w_bi_ptr_temp;
			w_gray_ptr<=((w_bi_ptr_temp)>>1)^(w_bi_ptr_temp);
		end
		if((w_bi_ptr_temp[2:0]==r_bi_sync[2:0])&&(w_bi_ptr_temp[3]!=r_bi_sync[3])) begin
			wfull<=1'b1;
		end
		else begin
		       wfull<=1'b0;
	       end
       end
end
endmodule

// read pointer handler

module read_handler(input rclk,
	input r_en,
	input r_rst,
	input [3:0]w_gray_sync,
	output reg [3:0]r_bi_ptr,
	output reg [3:0]r_gray_ptr,
	output reg rempty);

reg [3:0]w_bi_sync;
always@(*)begin
	w_bi_sync[3]=w_gray_sync[3];
	w_bi_sync[2]=w_bi_sync[3]^w_gray_sync[2];
	w_bi_sync[1]=w_bi_sync[2]^w_gray_sync[1];
	w_bi_sync[0]=w_bi_sync[1]^w_gray_sync[0];
end

always@(posedge rclk or negedge r_rst)begin
	if(!r_rst)begin
		r_bi_ptr<=4'd0;
		r_gray_ptr<= 4'd0;
		rempty<=1'b0;
	end
	else begin
		if(r_en && !rempty)begin
			r_bi_ptr<=r_bi_ptr+1;
			r_gray_ptr<=((r_bi_ptr+1)>>1)^(r_bi_ptr+1);
		end
		if(r_bi_ptr==w_bi_sync)begin
			rempty<=1'b1;
		end
		else begin
			rempty<=1'b0;
		end
	end
end
endmodule

//synchronizer
module synchronizer(input clk,
	input rst,
	input [3:0]gray_ptr,
	output reg[3:0]gray_sync);

reg [3:0]sync_ff1;

always@(posedge clk or negedge rst)begin
	if(!rst)begin
		sync_ff1<=4'd0;
		gray_sync<=4'd0;
	end
	else begin
		sync_ff1<=gray_ptr;
		gray_sync<=sync_ff1;
	end
end
endmodule


//top module

module async_fifo(input wclk,rclk,
	input w_en,r_en,
	input w_rst,r_rst,
	input [7:0]wdata,
	output  [7:0]rdata,
	output  wfull,
	output  rempty);

wire [3:0]w_bi_ptr;
wire [3:0]w_gray_ptr;
wire [3:0]w_gray_sync;

wire [3:0]r_bi_ptr;
wire [3:0]r_gray_ptr;
wire [3:0]r_gray_sync;

write_handler write(.wclk(wclk),
	.w_rst(w_rst),
	.w_en(w_en),
	.r_gray_sync(r_gray_sync),
	.w_bi_ptr(w_bi_ptr),
	.w_gray_ptr(w_gray_ptr),
	.wfull(wfull));

read_handler read(.rclk(rclk),
        .r_rst(r_rst),
        .r_en(r_en),
        .w_gray_sync(w_gray_sync),
        .r_bi_ptr(r_bi_ptr),
        .r_gray_ptr(r_gray_ptr),
        .rempty(rempty));

synchronizer sync_rptr(.clk(wclk),
	.rst(w_rst),
	.gray_ptr(r_gray_ptr),
	.gray_sync(r_gray_sync));

synchronizer sync_wptr(.clk(rclk),
        .rst(r_rst),
        .gray_ptr(w_gray_ptr),
        .gray_sync(w_gray_sync));

wire w_ena,r_ena;
assign w_ena=w_en && !wfull;
assign r_ena=r_en && !rempty;

memory mem(.wclk(wclk),
	.rclk(rclk),
	.w_en(w_ena),
	.w_add(w_bi_ptr[2:0]),
	.wdata(wdata),
	.r_en(r_ena),
	.r_add(r_bi_ptr[2:0]),
	.rdata(rdata));

endmodule

fifo/asynchronous_fifo/async_tb.v
`timescale 1ns/1ps

module async_fifo_tb;
reg wclk,rclk;
reg w_rst,r_rst;
reg w_en,r_en;
reg [7:0]wdata;
wire [7:0]rdata;
wire wfull;
wire rempty;

async_fifo uut(.wclk(wclk),
	.w_rst(w_rst),
	.w_en(w_en),
	.wdata(wdata),
	.rclk(rclk),
	.r_rst(r_rst),
	.r_en(r_en),
	.rdata(rdata),
	.wfull(wfull),
	.rempty(rempty));

always #5 wclk=~wclk;
always #10 rclk=~rclk;

initial begin
	wclk=0;
	rclk=0;
	w_rst=0;
	r_rst=0;
	w_en=0;
	r_en=0;
	wdata=8'b00000000;

	#20;
	w_rst=1;
	r_rst=1;

	#20;
	w_en=1;
	wdata=8'h11;#10;
	wdata=8'h22;#10;
	wdata=8'h33;#10;
	wdata=8'h44;#10;
	wdata=8'h55;#10;
	wdata=8'h66;#10;
	wdata=8'h77;#10;
	wdata=8'h88;#10;

	w_en=0;#30;
	r_en=1;
	#20;
	#20;
	#20;
	#20;
	#20;
	#20;
	#20;
	#20;
	r_en=0;
	#50;
	$finish;
end

always@(posedge wclk) begin
	$display("time=%0t w_e=%b wdata=%h full=%b",$time,w_en,wdata,wfull);
end

always@(posedge rclk) begin
        $display("time=%0t r_e=%b rdata=%h empty=%b",$time,r_en,rdata,rempty);
end

initial begin 
	$dumpfile("async_fifo.vcd");
	$dumpvars;
end
endmodule

fifo/asynchronous_fifo/async_fifo.vcd
$date
	Wed Sep  2 05:35:38 2026
$end
$version
	Icarus Verilog
$end
$timescale
	1ps
$end
$scope module async_fifo_tb $end
$var wire 1 ! wfull $end
$var wire 1 " rempty $end
$var wire 8 # rdata [7:0] $end
$var reg 1 $ r_en $end
$var reg 1 % r_rst $end
$var reg 1 & rclk $end
$var reg 1 ' w_en $end
$var reg 1 ( w_rst $end
$var reg 1 ) wclk $end
$var reg 8 * wdata [7:0] $end
$scope module uut $end
$var wire 1 $ r_en $end
$var wire 1 + r_ena $end
$var wire 1 % r_rst $end
$var wire 1 & rclk $end
$var wire 1 ' w_en $end
$var wire 1 , w_ena $end
$var wire 1 ( w_rst $end
$var wire 1 ) wclk $end
$var wire 8 - wdata [7:0] $end
$var wire 1 ! wfull $end
$var wire 4 . w_gray_sync [3:0] $end
$var wire 4 / w_gray_ptr [3:0] $end
$var wire 4 0 w_bi_ptr [3:0] $end
$var wire 1 " rempty $end
$var wire 8 1 rdata [7:0] $end
$var wire 4 2 r_gray_sync [3:0] $end
$var wire 4 3 r_gray_ptr [3:0] $end
$var wire 4 4 r_bi_ptr [3:0] $end
$scope module mem $end
$var wire 3 5 r_add [2:0] $end
$var wire 1 + r_en $end
$var wire 1 & rclk $end
$var wire 3 6 w_add [2:0] $end
$var wire 1 , w_en $end
$var wire 1 ) wclk $end
$var wire 8 7 wdata [7:0] $end
$var reg 8 8 rdata [7:0] $end
$upscope $end
$scope module read $end
$var wire 1 $ r_en $end
$var wire 1 % r_rst $end
$var wire 1 & rclk $end
$var wire 4 9 w_gray_sync [3:0] $end
$var reg 4 : r_bi_ptr [3:0] $end
$var reg 4 ; r_gray_ptr [3:0] $end
$var reg 1 " rempty $end
$var reg 4 < w_bi_sync [3:0] $end
$upscope $end
$scope module sync_rptr $end
$var wire 1 ) clk $end
$var wire 4 = gray_ptr [3:0] $end
$var wire 1 ( rst $end
$var reg 4 > gray_sync [3:0] $end
$var reg 4 ? sync_ff1 [3:0] $end
$upscope $end
$scope module sync_wptr $end
$var wire 1 & clk $end
$var wire 1 % rst $end
$var wire 4 @ gray_ptr [3:0] $end
$var reg 4 A gray_sync [3:0] $end
$var reg 4 B sync_ff1 [3:0] $end
$upscope $end
$scope module write $end
$var wire 4 C r_gray_sync [3:0] $end
$var wire 1 ' w_en $end
$var wire 1 ( w_rst $end
$var wire 1 ) wclk $end
$var wire 4 D w_bi_ptr_temp [3:0] $end
$var reg 4 E r_bi_sync [3:0] $end
$var reg 4 F w_bi_ptr [3:0] $end
$var reg 4 G w_gray_ptr [3:0] $end
$var reg 1 ! wfull $end
$upscope $end
$upscope $end
$upscope $end
$enddefinitions $end
$comment Show the parameter values. $end
$dumpall
$end
#0
$dumpvars
b0 G
b0 F
b0x E
b1 D
b0 C
b0 B
b0 A
b0 @
b0 ?
b0 >
b0 =
b0 <
b0 ;
b0 :
b0 9
bx 8
b0 7
b0 6
b0 5
b0 4
b0 3
b0 2
bx 1
b0 0
b0 /
b0 .
b0 -
0,
0+
b0 *
0)
0(
0'
0&
0%
0$
bx #
0"
0!
$end
#5000
1)
#10000
0)
1&
#15000
1)
#20000
0)
0&
1%
1(
#25000
1)
#30000
1"
0)
1&
#35000
1)
#40000
1,
0)
0&
b10001 *
b10001 -
b10001 7
1'
#45000
b1 6
b1 /
b1 @
b1 G
b10 D
b1 0
b1 F
1)
#50000
b1 B
0)
1&
b100010 *
b100010 -
b100010 7
#55000
b10 6
b11 /
b11 @
b11 G
b11 D
b10 0
b10 F
1)
#60000
0)
0&
b110011 *
b110011 -
b110011 7
#65000
b11 6
b10 /
b10 @
b10 G
b100 D
b11 0
b11 F
1)
#70000
b1 <
b1 .
b1 9
b1 A
b10 B
0)
1&
b1000100 *
b1000100 -
b1000100 7
#75000
b100 6
b110 /
b110 @
b110 G
b101 D
b100 0
b100 F
1)
#80000
0)
0&
b1010101 *
b1010101 -
b1010101 7
#85000
b101 6
b111 /
b111 @
b111 G
b110 D
b101 0
b101 F
1)
#90000
b11 <
b10 .
b10 9
b10 A
b111 B
0"
0)
1&
b1100110 *
b1100110 -
b1100110 7
#95000
b110 6
b101 /
b101 @
b101 G
b111 D
b110 0
b110 F
1)
#100000
0)
0&
b1110111 *
b1110111 -
b1110111 7
#105000
b111 6
b100 /
b100 @
b100 G
b1000 D
b111 0
b111 F
1)
#110000
b101 <
b111 .
b111 9
b111 A
b100 B
0)
1&
b10001000 *
b10001000 -
b10001000 7
#115000
b0 6
b1100 /
b1100 @
b1100 G
b1001 D
b1000 0
b1000 F
1)
#120000
0,
0)
0&
0'
#125000
1)
#130000
b111 <
b100 .
b100 9
b100 A
b1100 B
0)
1&
#135000
1)
#140000
0)
0&
#145000
1)
#150000
b1 5
b1000 <
b10001 #
b10001 1
b10001 8
b1 3
b1 ;
b1 =
b1 4
b1 :
b1100 .
b1100 9
b1100 A
1+
0)
1&
1$
#155000
b1 ?
1)
#160000
0)
0&
#165000
b10x E
b1 2
b1 >
b1 C
1)
#170000
b10 5
b100010 #
b100010 1
b100010 8
b11 3
b11 ;
b11 =
b10 4
b10 :
0)
1&
#175000
b11 ?
1)
#180000
0)
0&
#185000
b1x E
b11 2
b11 >
b11 C
1)
#190000
b11 5
b110011 #
b110011 1
b110011 8
b10 3
b10 ;
b10 =
b11 4
b11 :
0)
1&
#195000
b10 ?
1)
#200000
0)
0&
#205000
b11x E
b10 2
b10 >
b10 C
1)
#210000
b100 5
b1000100 #
b1000100 1
b1000100 8
b110 3
b110 ;
b110 =
b100 4
b100 :
0)
1&
#215000
b110 ?
1)
#220000
0)
0&
#225000
b0x E
b110 2
b110 >
b110 C
1)
#230000
b101 5
b1010101 #
b1010101 1
b1010101 8
b111 3
b111 ;
b111 =
b101 4
b101 :
0)
1&
#235000
b111 ?
1)
#240000
0)
0&
#245000
b10x E
b111 2
b111 >
b111 C
1)
#250000
b110 5
b1100110 #
b1100110 1
b1100110 8
b101 3
b101 ;
b101 =
b110 4
b110 :
0)
1&
#255000
b101 ?
1)
#260000
0)
0&
#265000
b1x E
b101 2
b101 >
b101 C
1)
#270000
b111 5
b1110111 #
b1110111 1
b1110111 8
b100 3
b100 ;
b100 =
b111 4
b111 :
0)
1&
#275000
b100 ?
1)
#280000
0)
0&
#285000
b11x E
b100 2
b100 >
b100 C
1)
#290000
b0 5
b10001000 #
b10001000 1
b10001000 8
b1100 3
b1100 ;
b1100 =
b1000 4
b1000 :
0)
1&
#295000
b1100 ?
1)
#300000
0)
0&
#305000
b100x E
b1100 2
b1100 >
b1100 C
1)
#310000
1"
0+
0)
1&
0$
