memories/fifo/fifo.v
module fifo(input clk,rst,
input w_en,rd_en,
input [3:0]d_in,
output reg [3:0]d_out,
output   full,empty);
reg [1:0]rd_ptr,w_ptr;
reg [3:0]mem[0:3];
reg [2:0]count;
always@(posedge clk)begin
if(rst)begin
	rd_ptr<=0;
	w_ptr<=0;
	count<=0;
	d_out<=0;
end
else begin
	if(w_en&&!rd_en && !full)begin
		mem[w_ptr]<=d_in;
		w_ptr<=w_ptr+1;
		count<=count+1;
	end
	if(rd_en && !w_en &&!empty)begin
		d_out<=mem[rd_ptr];
		rd_ptr<=rd_ptr+1;
		count<=count-1;
	end
end
end
assign empty=(count==0);
assign full=(count==4);
endmodule

memories/fifo/fifo_tb.v
module fifo_tb;
reg clk,rst;
reg w_en,rd_en;
reg [3:0]d_in;
wire [3:0]d_out;
wire full,empty;
fifo uut(.clk(clk),.rst(rst),.w_en(w_en),.rd_en(rd_en),.d_in(d_in),.d_out(d_out),.full(full),.empty(empty));
initial begin
clk=0;
forever #5 clk=~clk;
end
initial begin
	$monitor("clk=%b rst=%b w_en=%b d_in=%d rd_en=%b d_out=%d full=%b empty=%b",clk,rst,w_en,d_in,rd_en,d_out,full,empty);	
	$dumpfile("fifo.vcd");
	$dumpvars;
rst=1;
#10 rst=0;
w_en=1;
rd_en=0;

d_in=4'd2;
#10 d_in=4'd10;
#10 d_in=4'd9;
#10 d_in=4'd1;
#10 d_in=4'd6;
#10 rd_en=1;
w_en=0;
#60 $finish;
end
endmodule

memories/fifo/fifo.vcd
$date
	Mon Aug 31 11:24:32 2026
$end
$version
	Icarus Verilog
$end
$timescale
	1s
$end
$scope module fifo_tb $end
$var wire 1 ! full $end
$var wire 1 " empty $end
$var wire 4 # d_out [3:0] $end
$var reg 1 $ clk $end
$var reg 4 % d_in [3:0] $end
$var reg 1 & rd_en $end
$var reg 1 ' rst $end
$var reg 1 ( w_en $end
$scope module uut $end
$var wire 1 $ clk $end
$var wire 4 ) d_in [3:0] $end
$var wire 1 & rd_en $end
$var wire 1 ' rst $end
$var wire 1 ( w_en $end
$var wire 1 ! full $end
$var wire 1 " empty $end
$var reg 3 * count [2:0] $end
$var reg 4 + d_out [3:0] $end
$var reg 2 , rd_ptr [1:0] $end
$var reg 2 - w_ptr [1:0] $end
$upscope $end
$upscope $end
$enddefinitions $end
$comment Show the parameter values. $end
$dumpall
$end
#0
$dumpvars
bx -
bx ,
bx +
bx *
bx )
x(
1'
x&
bx %
0$
bx #
x"
x!
$end
#5
b0 #
b0 +
1"
0!
b0 *
b0 -
b0 ,
1$
#10
0$
b10 %
b10 )
0&
1(
0'
#15
b1 -
0"
b1 *
1$
#20
0$
b1010 %
b1010 )
#25
b10 -
b10 *
1$
#30
0$
b1001 %
b1001 )
#35
b11 -
b11 *
1$
#40
0$
b1 %
b1 )
#45
b0 -
1!
b100 *
1$
#50
0$
b110 %
b110 )
#55
1$
#60
0$
0(
1&
#65
b1 ,
b10 #
b10 +
0!
b11 *
1$
#70
0$
#75
b10 ,
b1010 #
b1010 +
b10 *
1$
#80
0$
#85
b11 ,
b1001 #
b1001 +
b1 *
1$
#90
0$
#95
b0 ,
b1 #
b1 +
1"
b0 *
1$
